ritsis/__init__.py
ritsis/sis.py
ritsis-0.6.dist-info/LICENSE
ritsis-0.6.dist-info/METADATA
ritsis-0.6.dist-info/WHEEL
ritsis-0.6.dist-info/top_level.txt
ritsis-0.6.dist-info/RECORD
