Metadata-Version: 2.1
Name: ritsis
Version: 0.6
Summary: Package for Sis
Home-page: UNKNOWN
Author: noidea
Author-email: noidea1238@gmail.com
License: UNKNOWN
Platform: UNKNOWN
Classifier: Programming Language :: Python :: 3
Classifier: License :: OSI Approved :: MIT License
Classifier: Operating System :: OS Independent
Requires-Python: >=3.6
Requires-Dist: robobrowser
Requires-Dist: Werkzeug (==0.16.1)
